lgtm_observe/__init__.py
lgtm_observe/cli.py
lgtm_observe/config.py
lgtm_observe/backends/__init__.py
lgtm_observe/backends/kafka.py
lgtm_observe/backends/loki.py
lgtm_observe/backends/prometheus.py
lgtm_observe/backends/tempo.py
adjoint_lgtm_observe-0.1.0.dist-info/METADATA
adjoint_lgtm_observe-0.1.0.dist-info/WHEEL
adjoint_lgtm_observe-0.1.0.dist-info/entry_points.txt
adjoint_lgtm_observe-0.1.0.dist-info/licenses/LICENSE
adjoint_lgtm_observe-0.1.0.dist-info/RECORD
