Metadata-Version: 2.4
Name: adjoint-lgtm-observe
Version: 0.1.0
Summary: Observability CLI for agentic workflows and event-driven systems. Query LGTM stack + Kafka from your terminal.
Project-URL: Homepage, https://github.com/adjoint-io/lgtm-observe
Project-URL: Documentation, https://github.com/adjoint-io/lgtm-observe#readme
Project-URL: Repository, https://github.com/adjoint-io/lgtm-observe
Project-URL: Issues, https://github.com/adjoint-io/lgtm-observe/issues
Author-email: Adjoint <engineering@adjoint.uk>
License: Apache-2.0
License-File: LICENSE
Keywords: agentic,ai-agents,cli,distributed-tracing,event-driven,grafana,kafka,lgtm,loki,observability,prometheus,tempo
Classifier: Development Status :: 3 - Alpha
Classifier: Environment :: Console
Classifier: Intended Audience :: Developers
Classifier: Intended Audience :: System Administrators
Classifier: License :: OSI Approved :: Apache Software License
Classifier: Programming Language :: Python :: 3
Classifier: Programming Language :: Python :: 3.10
Classifier: Programming Language :: Python :: 3.11
Classifier: Programming Language :: Python :: 3.12
Classifier: Topic :: System :: Logging
Classifier: Topic :: System :: Monitoring
Requires-Python: >=3.10
Provides-Extra: all
Requires-Dist: kafka-python>=2.0.0; extra == 'all'
Provides-Extra: dev
Requires-Dist: pytest-cov>=4.0.0; extra == 'dev'
Requires-Dist: pytest>=7.0.0; extra == 'dev'
Requires-Dist: ruff>=0.1.0; extra == 'dev'
Provides-Extra: kafka
Requires-Dist: kafka-python>=2.0.0; extra == 'kafka'
